walkman_modules/sound_file_players/__init__.py
walkman_modules.sound_file_player-0.2.0.dist-info/LICENSE
walkman_modules.sound_file_player-0.2.0.dist-info/METADATA
walkman_modules.sound_file_player-0.2.0.dist-info/WHEEL
walkman_modules.sound_file_player-0.2.0.dist-info/top_level.txt
walkman_modules.sound_file_player-0.2.0.dist-info/RECORD
