Metadata-Version: 2.1
Name: walkman-modules.sound-file-player
Version: 0.2.0
Summary: Provides walkman module to play sound files
Author: Levin Eric Zimmermann
Author-email: levin.eric.zimmermann@posteo.eu
License: GPL
Requires-Python: ==3.8
License-File: LICENSE
Requires-Dist: audiowalkman (<1.0.0,>=0.19.3)
Requires-Dist: SoundFile (>=0.10.3.post1)
Requires-Dist: numpy (<2.0.0,>=1.23.0)
Requires-Dist: pyo (<2.0.0,>=1.0.4)
Provides-Extra: testing
Requires-Dist: nose ; extra == 'testing'
